gitpyapi-1.0.0.dist-info/METADATA
gitpyapi-1.0.0.dist-info/WHEEL
gitpyapi-1.0.0.dist-info/entry_points.txt
gitpyapi-1.0.0.dist-info/license_files/LICENSE
gitpyapi.libs/libssl-a98fece2.so.3
gitpyapi.libs/libcrypto-93613d80.so.3
gitpyapi/__main__.py
gitpyapi/__init__.py
gitpyapi/gitpyapi.cpython-312-x86_64-linux-gnu.so
gitpyapi-1.0.0.dist-info/RECORD
